instruction_graph/__init__.py
instruction_graph/components/Memory.py
instruction_graph/components/PrimitiveLibrary.py
instruction_graph/components/PrimitiveTuples.py
instruction_graph/components/__init__.py
instruction_graph/core/IG.py
instruction_graph/core/Manager.py
instruction_graph/core/__init__.py
instruction_graph/example/DefaultMemory.py
instruction_graph/example/ExamplePrimitiveLibrary.py
instruction_graph/example/PepperController.py
instruction_graph/example/PepperMemory.py
instruction_graph/example/PepperPrimitiveLibrary.py
instruction_graph/example/__init__.py
instruction_graph/example/pepper_build.py
instruction_graph/example/pepper_run.py
instruction_graph/example/pepper_utils.py
instruction_graph/interactive/InteractiveManager.py
instruction_graph/interactive/TextCommunicator.py
instruction_graph/interactive/__init__.py
instruction_graph/interactive/utils.py
instruction_graph-0.2.23.data/scripts/run_itext_comm.py
instruction_graph-0.2.23.data/scripts/run_tests.py
instruction_graph-0.2.23.dist-info/DESCRIPTION.rst
instruction_graph-0.2.23.dist-info/METADATA
instruction_graph-0.2.23.dist-info/RECORD
instruction_graph-0.2.23.dist-info/WHEEL
instruction_graph-0.2.23.dist-info/metadata.json
instruction_graph-0.2.23.dist-info/top_level.txt
